ytdlp_simple/__init__.py
ytdlp_simple/bins.py
ytdlp_simple/config.py
ytdlp_simple/downloader.py
ytdlp_simple/ffmpeg.py
ytdlp_simple/log.py
ytdlp_simple/main.py
ytdlp_simple/paths.py
ytdlp_simple/type.py
ytdlp_simple/utils.py
ytdlp_simple/ytdlp.py
ytdlp_simple/bin/.gitkeep
ytdlp_simple/yt-dlp-plugins/extractor/invidious.py
ytdlp_simple/yt-dlp-plugins/extractor/youtube_override.py
ytdlp_simple-0.0.6.dist-info/METADATA
ytdlp_simple-0.0.6.dist-info/WHEEL
ytdlp_simple-0.0.6.dist-info/licenses/LICENSE
ytdlp_simple-0.0.6.dist-info/RECORD
