Metadata-Version: 2.4
Name: ytdlp-simple
Version: 0.0.6
Summary: Download videos and audio from YouTube and other platforms
Project-URL: Homepage, https://github.com/imbecility/ytdlp-simple
License-Expression: MIT
License-File: LICENSE
Classifier: Operating System :: Microsoft :: Windows
Classifier: Operating System :: POSIX :: Linux
Classifier: Programming Language :: Python :: 3
Classifier: Topic :: Multimedia
Requires-Python: >=3.10
